heartpy/__init__.py
heartpy/analysis.py
heartpy/config.py
heartpy/datautils.py
heartpy/exceptions.py
heartpy/filtering.py
heartpy/heartpy.py
heartpy/peakdetection.py
heartpy/preprocessing.py
heartpy/visualizeutils.py
heartpy/data/data.csv
heartpy/data/data.log
heartpy/data/data.mat
heartpy/data/data2.csv
heartpy/data/data2.log
heartpy/data/data2.mat
heartpy/data/data3.csv
heartpy/data/data3.mat
heartpy-1.2.7.dist-info/LICENSE
heartpy-1.2.7.dist-info/METADATA
heartpy-1.2.7.dist-info/WHEEL
heartpy-1.2.7.dist-info/top_level.txt
heartpy-1.2.7.dist-info/RECORD
