Metadata-Version: 2.1
Name: heartpy
Version: 1.2.7
Summary: Heart Rate Analysis Toolkit
Home-page: https://github.com/paulvangentcom/heartrate_analysis_python
Author: Paul van Gent
Author-email: P.vanGent@tudelft.nl
License: UNKNOWN
Platform: UNKNOWN
Classifier: Programming Language :: Python :: 2.7
Classifier: Programming Language :: Python :: 3.4
Classifier: Programming Language :: Python :: 3.5
Classifier: Programming Language :: Python :: 3.6
Classifier: Programming Language :: Python :: 3.7
Classifier: Programming Language :: Python :: 3.8
Classifier: License :: OSI Approved :: GNU General Public License (GPL)
Classifier: Operating System :: OS Independent
